olymap/__init__.py
olymap/char.py
olymap/detail.py
olymap/g4_index.txt
olymap/grey.gif
olymap/item.py
olymap/legacy.py
olymap/loc.py
olymap/make-oly-map.py
olymap/map.css
olymap/maps.py
olymap/player.py
olymap/reports.py
olymap/ship.py
olymap/skill.py
olymap/sorttable.js
olymap/storm.py
olymap/utilities.py
olymap/templates/char.html
olymap/templates/character_list.html
olymap/templates/index.html
olymap/templates/item.html
olymap/templates/loc.html
olymap/templates/loc_list.html
olymap/templates/loc_list_common.html
olymap/templates/map_leaf.html
olymap/templates/master_castle_report.html
olymap/templates/master_character_report.html
olymap/templates/master_city_report.html
olymap/templates/master_faeryhill_report.html
olymap/templates/master_gate_report.html
olymap/templates/master_gold_report.html
olymap/templates/master_graveyard_report.html
olymap/templates/master_healing_potion_report.html
olymap/templates/master_item_report.html
olymap/templates/master_location_report.html
olymap/templates/master_mage_report.html
olymap/templates/master_orb_report.html
olymap/templates/master_player_report.html
olymap/templates/master_priest_report.html
olymap/templates/master_projected_cast_report.html
olymap/templates/master_region_report.html
olymap/templates/master_road_report.html
olymap/templates/master_ship_report.html
olymap/templates/master_skill_xref_report.html
olymap/templates/master_trade_report.html
olymap/templates/player.html
olymap/templates/ship.html
olymap/templates/ship_list.html
olymap/templates/skill.html
olymap/templates/storm.html
olymap/templates/storm_list.html
olymap/templates/top_map.html
olypy/__init__.py
olypy/box.py
olypy/data.py
olypy/db.py
olypy/dbck.py
olypy/details.py
olypy/formatters.py
olypy/items.py
olypy/oid.py
olypy/oio.py
olypy/turnparser.py
olypy/mapgen-lib/email
olypy/mapgen-lib/forward
olypy/mapgen-lib/gate
olypy/mapgen-lib/item
olypy/mapgen-lib/loc
olypy/mapgen-lib/misc
olypy/mapgen-lib/players
olypy/mapgen-lib/randseed
olypy-0.9.45.dist-info/LICENSE
olypy-0.9.45.dist-info/METADATA
olypy-0.9.45.dist-info/WHEEL
olypy-0.9.45.dist-info/top_level.txt
olypy-0.9.45.dist-info/RECORD
