Metadata-Version: 2.1
Name: olypy
Version: 0.9.45
Summary: Python code to assist the game Olympia
Home-page: https://github.com/olympiag3/olypy
Author: Greg Lindahl and others
Author-email: lindahl@pbm.com
License: Apache 2.0
Platform: UNKNOWN
Classifier: Development Status :: 4 - Beta
Classifier: Environment :: Console
Classifier: Intended Audience :: End Users/Desktop
Classifier: Intended Audience :: Developers
Classifier: Natural Language :: English
Classifier: License :: OSI Approved :: Apache Software License
Classifier: Programming Language :: Python
Classifier: Programming Language :: Python :: 3.5
Classifier: Programming Language :: Python :: 3.6
Classifier: Programming Language :: Python :: 3.7
Classifier: Programming Language :: Python :: 3.8
Classifier: Programming Language :: Python :: 3.9
Classifier: Programming Language :: Python :: 3 :: Only
Requires-Python: >=3.5.*
Requires-Dist: PyYAML
Requires-Dist: pngcanvas
